api/__init__.py
api/admin.py
api/apps.py
api/models.py
api/tests.py
api/views.py
api/migrations/__init__.py
core/__init__.py
core/admin.py
core/asgi.py
core/schema.py
core/settings.py
core/urls.py
core/wsgi.py
db/__init__.py
db/admin.py
db/apps.py
db/init.py
db/models.py
db/schema.py
db/tests.py
db/validators.py
db/graphene/__init__.py
db/graphene/enums/__init__.py
db/graphene/objecttypes/__init__.py
db/migrations/0001_initial.py
db/migrations/__init__.py
editorjs/__init__.py
editorjs/admin.py
editorjs/apps.py
editorjs/fields.py
editorjs/models.py
editorjs/tests.py
editorjs/views.py
editorjs/widgets.py
editorjs/migrations/__init__.py
web/__init__.py
web/admin.py
web/apps.py
web/tests.py
web/urls.py
web/context_processors/__init__.py
web/context_processors/_global_context.py
web/context_processors/_sections.py
web/forms/___form.py
web/forms/___model_form.py
web/forms/___multi_form.py
web/forms/__contact_form.py
web/forms/__control_center_form.py
web/forms/__init__.py
web/forms/__login_form.py
web/forms/__logout_form.py
web/forms/__preferences_form.py
web/forms/__profile_form.py
web/forms/__register_form.py
web/forms/_admonition_action_form.py
web/forms/_admonition_form.py
web/forms/_admonition_template_form.py
web/forms/_alert_form.py
web/forms/_book_form.py
web/forms/_book_part_form.py
web/forms/_comment_form.py
web/forms/_contest_form.py
web/forms/_correction_request_form.py
web/forms/_faq_form.py
web/forms/_license_form.py
web/forms/_member_form.py
web/forms/_message_form.py
web/forms/_post_form.py
web/forms/_site_param_form.py
web/forms/_tag_form.py
web/forms/_theme_selector_form.py
web/forms/widgets/__init__.py
web/forms/widgets/tags_select_input.py
web/middlewares/__init__.py
web/middlewares/muses_pages_views.py
web/middlewares/muses_params.py
web/migrations/__init__.py
web/templatetags/__init__.py
web/templatetags/user_tags.py
web/views/__init__.py
web/views/views.py
web/views/generic/__init__.py
web/views/generic/admin_create_view.py
muses_lpdp-0.3.1589114859.dist-info/LICENSE
muses_lpdp-0.3.1589114859.dist-info/METADATA
muses_lpdp-0.3.1589114859.dist-info/WHEEL
muses_lpdp-0.3.1589114859.dist-info/top_level.txt
muses_lpdp-0.3.1589114859.dist-info/RECORD
