Metadata-Version: 2.1
Name: muses-lpdp
Version: 0.3.1589114859
Summary: Muses from La Passion des Poèmes.
Home-page: https://gitlab.com/lpdp/muses/-/wikis/Accueil
Author: Eric Laugier
Author-email: devteam@lapassiondespoemes.com
License: GNU Lesser General Public License v3 (LGPLv3)
Platform: UNKNOWN
Classifier: Development Status :: 3 - Alpha
Classifier: Environment :: Web Environment
Classifier: Framework :: Django :: 3.0
Classifier: Intended Audience :: End Users/Desktop
Classifier: License :: OSI Approved :: GNU Lesser General Public License v3 (LGPLv3)
Classifier: Operating System :: OS Independent
Classifier: Programming Language :: Python
Classifier: Programming Language :: Python :: 3
Classifier: Programming Language :: Python :: 3 :: Only
Classifier: Programming Language :: Python :: 3.6
Classifier: Programming Language :: Python :: 3.7
Classifier: Programming Language :: Python :: 3.8
Classifier: Topic :: Internet :: WWW/HTTP
Classifier: Topic :: Internet :: WWW/HTTP :: Dynamic Content
Requires-Dist: alabaster (==0.7.12)
Requires-Dist: algorithm (==1.2.0)
Requires-Dist: aniso8601 (==7.0.0)
Requires-Dist: appdirs (==1.4.3)
Requires-Dist: argon2-cffi (==19.2.0)
Requires-Dist: asgiref (==3.2.7)
Requires-Dist: Babel (==2.8.0)
Requires-Dist: bcrypt (==3.1.7)
Requires-Dist: bleach (==3.1.5)
Requires-Dist: certifi (==2020.4.5.1)
Requires-Dist: cffi (==1.14.0)
Requires-Dist: chardet (==3.0.4)
Requires-Dist: colorama (==0.4.3)
Requires-Dist: dependency-injection (==1.2.0)
Requires-Dist: distlib (==0.3.0)
Requires-Dist: Django (==3.0.5)
Requires-Dist: django-appconf (==1.0.4)
Requires-Dist: django-debug-toolbar (==2.2)
Requires-Dist: django-editorjs-field (==0.0.3)
Requires-Dist: django-filter (==2.2.0)
Requires-Dist: django-otp (==0.9.0)
Requires-Dist: django-phonenumber-field (==4.0.0)
Requires-Dist: django-precise-bbcode (==1.2.12)
Requires-Dist: django-qr-code (==1.2.0)
Requires-Dist: docutils (==0.16)
Requires-Dist: filelock (==3.0.12)
Requires-Dist: filesystem-tree (==1.1.2)
Requires-Dist: first (==2.0.2)
Requires-Dist: geoip2 (==3.0.0)
Requires-Dist: graphene (==2.1.8)
Requires-Dist: graphene-django (==2.9.1)
Requires-Dist: graphql-core (==2.3.1)
Requires-Dist: graphql-relay (==2.0.1)
Requires-Dist: idna (==2.9)
Requires-Dist: imagesize (==1.2.0)
Requires-Dist: importlib-metadata (==1.6.0)
Requires-Dist: Jinja2 (==2.11.2)
Requires-Dist: keyring (==21.2.1)
Requires-Dist: lorem (==0.1.1)
Requires-Dist: markdown2 (==2.3.8)
Requires-Dist: MarkupSafe (==1.1.1)
Requires-Dist: maxminddb (==1.5.2)
Requires-Dist: numpy (==1.18.3)
Requires-Dist: packaging (==20.3)
Requires-Dist: phonenumbers (==8.12.2)
Requires-Dist: Pillow (==7.1.2)
Requires-Dist: pkginfo (==1.5.0.1)
Requires-Dist: pluggy (==0.13.1)
Requires-Dist: promise (==2.3)
Requires-Dist: psycopg2-binary (==2.8.5)
Requires-Dist: py (==1.8.1)
Requires-Dist: pycparser (==2.20)
Requires-Dist: Pygments (==2.6.1)
Requires-Dist: pyparsing (==2.4.7)
Requires-Dist: pyspellchecker (==0.5.4)
Requires-Dist: python-mimeparse (==1.6.0)
Requires-Dist: pytz (==2020.1)
Requires-Dist: pywin32-ctypes (==0.2.0)
Requires-Dist: qrcode (==6.1)
Requires-Dist: readme-renderer (==26.0)
Requires-Dist: requests (==2.23.0)
Requires-Dist: requests-toolbelt (==0.9.1)
Requires-Dist: ruamel.yaml (==0.16.10)
Requires-Dist: ruamel.yaml.clib (==0.2.0)
Requires-Dist: Rx (==1.6.1)
Requires-Dist: singledispatch (==3.4.0.3)
Requires-Dist: six (==1.14.0)
Requires-Dist: snowballstemmer (==2.0.0)
Requires-Dist: Sphinx (==3.0.3)
Requires-Dist: sphinxcontrib-applehelp (==1.0.2)
Requires-Dist: sphinxcontrib-devhelp (==1.0.2)
Requires-Dist: sphinxcontrib-htmlhelp (==1.0.3)
Requires-Dist: sphinxcontrib-jsmath (==1.0.1)
Requires-Dist: sphinxcontrib-qthelp (==1.0.3)
Requires-Dist: sphinxcontrib-serializinghtml (==1.1.4)
Requires-Dist: sqlparse (==0.3.1)
Requires-Dist: toml (==0.10.0)
Requires-Dist: tox (==3.15.0)
Requires-Dist: tqdm (==4.46.0)
Requires-Dist: twine (==3.1.1)
Requires-Dist: urllib3 (==1.25.9)
Requires-Dist: virtualenv (==20.0.18)
Requires-Dist: webencodings (==0.5.1)
Requires-Dist: zipp (==3.1.0)
